object_filtering/__init__.py
object_filtering/object_filtering.py
object_filtering/natural_language/__init__.py
object_filtering/natural_language/natural_language.py
object_filtering-0.1.14.dist-info/METADATA
object_filtering-0.1.14.dist-info/WHEEL
object_filtering-0.1.14.dist-info/licenses/LICENSE.txt
object_filtering-0.1.14.dist-info/RECORD
