Metadata-Version: 2.4
Name: object_filtering
Version: 0.1.14
Summary: A module for determining whether arbitrary Python objects meet a set of defined criteria.
Project-URL: Homepage, https://github.com/KyberCritter/Object-Filtering
Project-URL: Issues, https://github.com/KyberCritter/Object-Filtering/issues
Author-email: Scott Ratchford <object_filtering@scottratchford.com>
License-File: LICENSE.txt
Classifier: Development Status :: 4 - Beta
Classifier: Intended Audience :: Developers
Classifier: License :: OSI Approved :: MIT License
Classifier: Natural Language :: English
Classifier: Programming Language :: Python :: 3.10
Classifier: Programming Language :: Python :: 3.11
Classifier: Programming Language :: Python :: 3.12
Classifier: Programming Language :: Python :: 3.13
Classifier: Topic :: File Formats :: JSON
Classifier: Topic :: Software Development :: Libraries :: Python Modules
Classifier: Topic :: Utilities
Requires-Python: >=3.10
Requires-Dist: numpy>=2.0.0
